psycopg2-stubs/METADATA.toml
psycopg2-stubs/__init__.pyi
psycopg2-stubs/_ipaddress.pyi
psycopg2-stubs/_json.pyi
psycopg2-stubs/_psycopg.pyi
psycopg2-stubs/_range.pyi
psycopg2-stubs/errorcodes.pyi
psycopg2-stubs/errors.pyi
psycopg2-stubs/extensions.pyi
psycopg2-stubs/extras.pyi
psycopg2-stubs/pool.pyi
psycopg2-stubs/py.typed
psycopg2-stubs/sql.pyi
psycopg2-stubs/tz.pyi
types_psycopg2-2.9.21.20250318.dist-info/LICENSE
types_psycopg2-2.9.21.20250318.dist-info/METADATA
types_psycopg2-2.9.21.20250318.dist-info/WHEEL
types_psycopg2-2.9.21.20250318.dist-info/top_level.txt
types_psycopg2-2.9.21.20250318.dist-info/RECORD
